shinier/ImageDataset.py
shinier/ImageListIO.py
shinier/ImageProcessor.py
shinier/Options.py
shinier/SHINIER.py
shinier/__init__.py
shinier/_cconvolve.cpp
shinier/_cconvolve.cpython-312-darwin.so
shinier/base.py
shinier/build_ext.py
shinier/utils.py
shinier/color/Converter.py
shinier/color/M_RGB2XYZ_2020.npy
shinier/color/M_RGB2XYZ_601.npy
shinier/color/M_RGB2XYZ_709.npy
shinier/color/__init__.py
shinier/data/INPUT/test_face1.jpeg
shinier/data/INPUT/test_face2.jpeg
shinier/data/INPUT/test_face3.jpeg
shinier/data/INPUT/test_face4.jpeg
shinier/data/INPUT/test_face5.jpeg
shinier/data/INPUT/test_scene1.jpeg
shinier/data/INPUT/test_scene2.jpeg
shinier/data/INPUT/test_scene3.jpeg
shinier/data/INPUT/test_scene4.jpeg
shinier/data/INPUT/test_scene5.jpeg
shinier/data/MASK/mask.png
shinier/data/OUTPUT/.gitkeep
shinier-0.1.8.dist-info/licenses/LICENSE
shinier-0.1.8.dist-info/METADATA
shinier-0.1.8.dist-info/WHEEL
shinier-0.1.8.dist-info/entry_points.txt
shinier-0.1.8.dist-info/top_level.txt
shinier-0.1.8.dist-info/RECORD
