Metadata-Version: 2.4
Name: shinier
Version: 0.1.8
Summary: Python port of the SHINE toolbox with added options (color management, dithering, EHS), optimized for large image sets.
Author-email: Nicolas Dupuis-Roy <nicolas.dupuis.roy@umontreal.ca>, Mathias Salvas-Hébert <mathias.salvas-hebert@umontreal.ca>
License: MIT
Project-URL: Homepage, https://github.com/Charestlab/shinier
Classifier: Programming Language :: Python :: 3.9
Classifier: Programming Language :: Python :: 3.10
Classifier: Programming Language :: Python :: 3.11
Classifier: Programming Language :: Python :: 3.12
Classifier: License :: OSI Approved :: MIT License
Classifier: Operating System :: OS Independent
Requires-Python: <3.13,>=3.9
License-File: LICENSE
Requires-Dist: numpy<2.1,>=1.22
Requires-Dist: Pillow>=9.0.0
Requires-Dist: tqdm>=4.60
Requires-Dist: cython>=3.0
Requires-Dist: matplotlib>=3.9.0
Requires-Dist: pydantic>=2.12
Provides-Extra: dev
Requires-Dist: pytest>=8.3.0; extra == "dev"
Requires-Dist: wheel>=0.44.0; extra == "dev"
Requires-Dist: setuptools>=74.1; extra == "dev"
Requires-Dist: scikit-image>=0.24.0; extra == "dev"
Requires-Dist: colour-science>=0.4.0; extra == "dev"
Requires-Dist: build>=1.2.1; extra == "dev"
Requires-Dist: pytest-xdist>=3.8.0; extra == "dev"
Dynamic: license-file
